nsloader/__init__.py
nsloader/wsj.py
test/__init__.py
test/test_wsj.py
nsloader-1.1.0.dist-info/LICENSE
nsloader-1.1.0.dist-info/METADATA
nsloader-1.1.0.dist-info/WHEEL
nsloader-1.1.0.dist-info/top_level.txt
nsloader-1.1.0.dist-info/RECORD
