Metadata-Version: 2.1
Name: nsloader
Version: 1.1.0
Summary: This script collects articles from Wall Street Journal and returns it in dict format.
Home-page: https://github.com/new-village/nsloader
Author: new-village
License-File: LICENSE
Requires-Dist: playwright
